hvneuro/__init__.py
hvneuro/vidviewer.py
hvneuro-0.1.0a1.dist-info/LICENSE.txt
hvneuro-0.1.0a1.dist-info/METADATA
hvneuro-0.1.0a1.dist-info/WHEEL
hvneuro-0.1.0a1.dist-info/top_level.txt
hvneuro-0.1.0a1.dist-info/RECORD
