Metadata-Version: 2.1
Name: hvneuro
Version: 0.1.0a1
Summary: Neuroscience visualization with HoloViz
Author-email: Demetris Roumis <8qdo8efl3@mozmail.com>
Requires-Python: >=3.8
License-File: LICENSE.txt
Requires-Dist: numpy
Requires-Dist: xarray
Requires-Dist: holoviews
Requires-Dist: panel
Requires-Dist: hvplot
Requires-Dist: datashader
Requires-Dist: bokeh
